yummy_mlflow-0.0.9.dist-info/METADATA
yummy_mlflow-0.0.9.dist-info/WHEEL
yummy_mlflow-0.0.9.dist-info/license_files/LICENSE
yummy_mlflow.libs/libgomp-e80b85fe.so.1
yummy_mlflow/__init__.py
yummy_mlflow/yummy_mlflow.cpython-39-x86_64-linux-gnu.so
yummy_mlflow-0.0.9.dist-info/RECORD
